histstat/__init__.py
histstat/histstat.py
histstat-1.1.0.dist-info/LICENSE
histstat-1.1.0.dist-info/METADATA
histstat-1.1.0.dist-info/WHEEL
histstat-1.1.0.dist-info/entry_points.txt
histstat-1.1.0.dist-info/top_level.txt
histstat-1.1.0.dist-info/RECORD
