Metadata-Version: 2.1
Name: histstat
Version: 1.1.0
Summary: History for netstat.
Home-page: https://github.com/vesche/histstat
Author: Austin Jackson
Author-email: vesche@protonmail.com
License: MIT
Platform: UNKNOWN
Classifier: Development Status :: 5 - Production/Stable
Classifier: Environment :: Console
Classifier: Intended Audience :: Information Technology
Classifier: License :: OSI Approved :: MIT License
Classifier: Programming Language :: Python :: 2
Classifier: Programming Language :: Python :: 2.7
Classifier: Programming Language :: Python :: 3
Classifier: Programming Language :: Python :: 3.6
Classifier: Topic :: Security
Requires-Dist: psutil
